MANIFEST.in
README.rst
setup.cfg
setup.py
timers/__init__.py
timers/heap.py
timers.egg-info/PKG-INFO
timers.egg-info/SOURCES.txt
timers.egg-info/dependency_links.txt
timers.egg-info/top_level.txt