Metadata-Version: 1.0
Name: timers
Version: 0.9.2
Summary: Python Timer Library
Home-page: https://github.com/choppsv1/pytimers
Author: Christian E. Hopps
Author-email: chopps@gmail.com
License: Apache License, Version 2.0
Platform: UNKNOWN
